svbmc/__init__.py
svbmc/svbmc.py
svbmc/targets.py
svbmc/utils.py
svbmc-0.1.1.dist-info/licenses/LICENSE.txt
svbmc-0.1.1.dist-info/METADATA
svbmc-0.1.1.dist-info/WHEEL
svbmc-0.1.1.dist-info/top_level.txt
svbmc-0.1.1.dist-info/RECORD
