Metadata-Version: 2.4
Name: svbmc
Version: 0.1.1
Summary: Stacking Variational Bayesian Monte Carlo
License: BSD 3-Clause License
Requires-Python: >=3.11
License-File: LICENSE.txt
Requires-Dist: numpy>=2.3
Requires-Dist: scipy>=1.16
Requires-Dist: torch>=2.7
Requires-Dist: corner>=2.2
Requires-Dist: matplotlib>=3.10
Requires-Dist: GPyReg>=1.0.2
Requires-Dist: pyvbmc>=1.0.4
Dynamic: license-file
